hopes/__init__.py
hopes/assert_utils.py
hopes/dev_utils.py
hopes/ope/__init__.py
hopes/ope/estimators.py
hopes/ope/evaluation.py
hopes/ope/selection.py
hopes/policy/__init__.py
hopes/policy/onnx.py
hopes/policy/policies.py
hopes/policy/spaces.py
hopes/policy/utils.py
hopes/rew/__init__.py
hopes/rew/rewards.py
hopes-0.0.1.dist-info/LICENSE
hopes-0.0.1.dist-info/METADATA
hopes-0.0.1.dist-info/WHEEL
hopes-0.0.1.dist-info/entry_points.txt
hopes-0.0.1.dist-info/RECORD
