Metadata-Version: 2.1
Name: hopes
Version: 0.0.1
Summary: HVAC Off-policy evaluation and selection methods
Author: Antoine Galataud
Author-email: antoine@foobot.io
Requires-Python: >=3.10,<3.11
Classifier: Programming Language :: Python :: 3
Classifier: Programming Language :: Python :: 3.10
Requires-Dist: PyYAML (>=6.0.1,<6.1.0)
Requires-Dist: boto3 (>=1.34.74,<2.0.0)
Requires-Dist: dataclasses-json (==0.6.7)
Requires-Dist: matplotlib (==3.9.0)
Requires-Dist: numpy (==1.26.4)
Requires-Dist: onnxruntime (==1.18.0)
Requires-Dist: pandas (==2.2.2)
Requires-Dist: pwlf (==2.2.1)
Requires-Dist: pytz (==2024.1)
Requires-Dist: requests (==2.32.3)
Requires-Dist: scikit-learn (==1.5.0)
Requires-Dist: tabulate (==0.9.0)
Requires-Dist: torch (==2.3.1)
Requires-Dist: urllib3 (==2.2.1)
